soda/data_sources/mysql_data_source.py
soda_core_mysql_utf8_hotfix-3.5.5.post1.dist-info/licenses/LICENSE
soda_core_mysql_utf8_hotfix-3.5.5.post1.dist-info/METADATA
soda_core_mysql_utf8_hotfix-3.5.5.post1.dist-info/WHEEL
soda_core_mysql_utf8_hotfix-3.5.5.post1.dist-info/top_level.txt
soda_core_mysql_utf8_hotfix-3.5.5.post1.dist-info/RECORD
