Metadata-Version: 2.4
Name: soda-core-mysql-utf8-hotfix
Version: 3.5.5.post1
Summary: Soda Core MySQL Package - UTF8 Charset Hotfix
Home-page: https://github.com/addiewan/soda-core
License-File: LICENSE
Requires-Dist: soda-core==3.5.5
Requires-Dist: mysql-connector-python==8.0.33
Dynamic: description
Dynamic: description-content-type
Dynamic: home-page
Dynamic: license-file
Dynamic: requires-dist
Dynamic: summary
